insights_engine/__init__.py
insights_engine/api_client.py
insights_engine/configuration.py
insights_engine/exceptions.py
insights_engine/model_utils.py
insights_engine/rest.py
insights_engine/api/__init__.py
insights_engine/api/filter_api.py
insights_engine/api/groups_api.py
insights_engine/api/insights_api.py
insights_engine/api/metrics_api.py
insights_engine/api/save_api.py
insights_engine/api/subscriptions_api.py
insights_engine/api/user_api.py
insights_engine/apis/__init__.py
insights_engine/model/__init__.py
insights_engine/model/add_filter_batch_input.py
insights_engine/model/add_filter_batch_output.py
insights_engine/model/add_filter_input.py
insights_engine/model/add_filter_output.py
insights_engine/model/add_members_input.py
insights_engine/model/add_members_output.py
insights_engine/model/add_subscription_input.py
insights_engine/model/add_user_input.py
insights_engine/model/add_user_output.py
insights_engine/model/context.py
insights_engine/model/create_group_input.py
insights_engine/model/create_group_output.py
insights_engine/model/delete_batch_filter_output.py
insights_engine/model/delete_filter_batch_input.py
insights_engine/model/delete_filter_input.py
insights_engine/model/delete_filter_output.py
insights_engine/model/delete_group_members_input.py
insights_engine/model/delete_subscription_input.py
insights_engine/model/filter.py
insights_engine/model/filter_out.py
insights_engine/model/get_all_admin_groups_output.py
insights_engine/model/get_filter_output.py
insights_engine/model/get_group_admins_output.py
insights_engine/model/get_group_insights_output.py
insights_engine/model/get_group_members_ouput.py
insights_engine/model/get_real_time_insights_input.py
insights_engine/model/get_real_time_insights_output.py
insights_engine/model/get_user_insights_output.py
insights_engine/model/get_user_output.py
insights_engine/model/get_user_subscriptions_output.py
insights_engine/model/group_description.py
insights_engine/model/insight_payload.py
insights_engine-1.0.14.dist-info/METADATA
insights_engine-1.0.14.dist-info/WHEEL
insights_engine-1.0.14.dist-info/top_level.txt
insights_engine-1.0.14.dist-info/RECORD
