Metadata-Version: 2.1
Name: insights-engine
Version: 1.0.14
Summary: Proxy Service
Home-page: UNKNOWN
Author: OpenAPI Generator community
Author-email: eden.trainor@compassdigital.io
License: Apache 2.0
Keywords: OpenAPI,OpenAPI-Generator,Proxy Service
Platform: UNKNOWN
Requires-Python: >=3.6
Requires-Dist: urllib3 (>=1.25.3)
Requires-Dist: python-dateutil
